zimply/__init__.py
zimply/template.html
zimply/zimply.py
zimply-1.1.3.dist-info/LICENSE.txt
zimply-1.1.3.dist-info/METADATA
zimply-1.1.3.dist-info/WHEEL
zimply-1.1.3.dist-info/top_level.txt
zimply-1.1.3.dist-info/RECORD
