Metadata-Version: 2.1
Name: zimply
Version: 1.1.3
Summary: ZIMply is an easy to use, offline reader for Wikipedia - as well as other ZIM files - which provides access to them through any ordinary browser.
Home-page: https://github.com/kimbauters/ZIMply
Author: Kim Bauters
Author-email: kim.bauters@gmail.com
License: MIT
Download-URL: https://github.com/kimbauters/ZIMply/tarball/1.1.3
Keywords: zim,wiki,wikipedia
Platform: any
Classifier: Programming Language :: Python :: 3.4
Classifier: License :: OSI Approved :: MIT License
Classifier: Development Status :: 5 - Production/Stable
Requires-Dist: gevent (>=1.1.1)
Requires-Dist: falcon (>=1.0.0)
Requires-Dist: mako (>=1.0.3)
